mabu/__init__.py
mabu/mabu.py
mabu-0.0.2.dist-info/METADATA
mabu-0.0.2.dist-info/WHEEL
mabu-0.0.2.dist-info/licenses/LICENSE
mabu-0.0.2.dist-info/RECORD
